<?xml version="1.0" encoding="utf-8" ?><dwsync><file name="allerton.php" server="79.170.44.20" local="3459260450" remote="16344158688" /><file name="bingley.php" server="79.170.44.20" local="3459260438" remote="16344158688" /><file name="buttershaw.php" server="79.170.44.20" local="3459260426" remote="16344158688" /><file name="clayton.php" server="79.170.44.20" local="3459260420" remote="16344158688" /><file name="cottingley.php" server="79.170.44.20" local="3459260412" remote="16344158688" /><file name="cullingworth.php" server="79.170.44.20" local="3459260500" remote="16344158748" /><file name="denholme.php" server="79.170.44.20" local="3459260494" remote="16344158748" /><file name="eldwick.php" server="79.170.44.20" local="3459260487" remote="16344158748" /><file name="harden.php" server="79.170.44.20" local="3459260480" remote="16344158748" /><file name="norr.php" server="79.170.44.20" local="3459260551" remote="16344158808" /><file name="queensbury.php" server="79.170.44.20" local="3459260544" remote="16344158808" /><file name="thornton.php" server="79.170.44.20" local="3459260538" remote="16344158808" /><file name="wibsey.php" server="79.170.44.20" local="3459260532" remote="16344158808" /><file name="wilsden.php" server="79.170.44.20" local="3459260525" remote="16344158808" /><file name="index.php" server="79.170.44.20" local="3459260511" remote="16344158748" /><file name="areas-covered.php" server="79.170.44.20" local="3459494546" remote="16344392808" /><file name="bradford.php" server="79.170.44.20" local="3465794318" remote="16350696168" /></dwsync>